[{"event":"DUATHLON DE GUINGAMP","organisateur":null,"lieu":"GUINGAMP","departement":"22","divers":"GUINGAMP TRIATHLON 0760937462 - pascal.esneu@gmail.com","email":"pascal.esneu@gmail.com"},{"event":"TRIATHLON DU PAYS DE RANCE","organisateur":null,"lieu":"TADEN","departement":"22","divers":"DINAN TRIATHLON site internet : http://www.dinan-triathlon.fremail : contact@dinan-triathlon.fr https://www.klikego.com/","email":"contact@dinan-triathlon.fr"},{"event":"TRIATHLON DU PAYS DE RANCE","organisateur":null,"lieu":"TADEN","departement":"22","divers":"DINAN TRIATHLON site internet : http://www.dinan-triathlon.fremail : contact@dinan-triathlon.fr https://www.klikego.com/","email":"contact@dinan-triathlon.fr"},{"event":"RAID DES 2 RIVIèRES","organisateur":null,"lieu":"QUEMPER-GUEZENNEC","departement":"22","divers":"COMITé D'ANIMATION DE QUEMPER-GUEZENNEC0789591182 - raiddes2rivieres@gmail.com","email":"raiddes2rivieres@gmail.com"},{"event":"TRIATHLON DU VAL ANDRE","organisateur":null,"lieu":"PLENEUF VAL ANDRE","departement":"22","divers":"VAL-ANDRé TRIATHLONwww.triathlonduvalandre.comcontact@triathlonduvalandre.comwww.klikego.com","email":"TRIATHLONwww.triathlonduvalandre.comcontact@triathlonduvalandre.comwww.klikego.com"},{"event":"EN'TRIATHLON - TRIATHLON ENTREPRISES","organisateur":null,"lieu":"BREST","departement":"29","divers":"BREST TRIATHLON entriathlon@gmail.com klikego.com","email":"entriathlon@gmail.com"},{"event":"DUATHLON DE LAMPAUL GUIMILIAU","organisateur":null,"lieu":"LAMPAUL GUIMILIAU","departement":"29","divers":"TEAM LANDI TRIATHLON 0635900613 - jeanchristophearros@gmail.com http://duathlonslampaulguimiliau.cd.st/","email":"jeanchristophearros@gmail.com"},{"event":"TRIATHLON DU MOULIN BLANC","organisateur":null,"lieu":"BREST","departement":"29","divers":"BREST TRIATHLON brest.triathlon@gmail.com klikego.com","email":"brest.triathlon@gmail.com"},{"event":"IROISE SWIMRUN","organisateur":null,"lieu":"PLOUGONVELIN","departement":"29","divers":"IROISE TRIATHLON loren.auffret@gmail.com","email":"loren.auffret@gmail.com"},{"event":"TRIATHLON DU PAYS DE QUIMPERLE","organisateur":null,"lieu":"CLOHARS CARNOET","departement":"29","divers":"KEMPERLE TRIATHLON 0618883390 - cedricjeunet@sfr.fr www.kemperletriathlon.fr","email":"cedricjeunet@sfr.fr"},{"event":"SWIM RUN AQUARANTEC","organisateur":null,"lieu":"CARANTEC","departement":"29","divers":"LES TRIATHLETES DE LA BAIE aquarantec@gmail.com klikego","email":"aquarantec@gmail.com"},{"event":"TRIBREIZH","organisateur":null,"lieu":"SIZUN","departement":"29","divers":"TRIBREIZH ORGANISATION 0298205271 - steflo.touvron@gmail.com http://tribreizh.org/","email":"steflo.touvron@gmail.com"},{"event":"TRIATHLON DE QUIMPER","organisateur":null,"lieu":"QUIMPER","departement":"29","divers":"QUIMPER TRIATHLON 0647387926 - triathlonquimper2017@gmail.com KLIKEGO.COM","email":"triathlonquimper2017@gmail.com"},{"event":"PLOUESCAT-TRIATHLON","organisateur":null,"lieu":"PLOUESCAT","departement":"29","divers":"PLOUESCAT- TRIATHLON 0298698140 - jean-jacques.bellec@wanadoo.fr http://www.tiptiptop.top","email":"jean-jacques.bellec@wanadoo.fr"},{"event":"TRILOKI - LES TRIATHLONS DURABLES DE LA BAIE DE LOCQUIREC","organisateur":null,"lieu":"LOCQUIREC","departement":"29","divers":"LES TRIATHLETES DE LA BAIE 0672759000 - triathlonlocquirec@gmail.com www.klikego.com","email":"triathlonlocquirec@gmail.com"},{"event":"TRILOKI - LES TRIATHLONS DURABLES DE LA BAIE DE LOCQUIREC","organisateur":null,"lieu":"LOCQUIREC","departement":"29","divers":"LES TRIATHLETES DE LA BAIE 0672759000 - triathlonlocquirec@gmail.com www.klikego.com","email":"triathlonlocquirec@gmail.com"},{"event":"TRIATHLON DE SAINT GRéGOIRE","organisateur":null,"lieu":"SAINT GREGOIRE","departement":"35","divers":"SAINT GRéGOIRE TRIATHLON inscription@triathlon-saint-gregoire.fr http://triathlon-saint-gregoire.fr/","email":"inscription@triathlon-saint-gregoire.fr"},{"event":"XXL CORSAIRE","organisateur":null,"lieu":"SAINT MALO","departement":"35","divers":"XXL CORSAIRE contact@xxl-corsaire.fr www.xxl-corsaire.fr","email":"contact@xxl-corsaire.fr"},{"event":"TRIATHLON DE CESSON SéVIGNé 2018","organisateur":null,"lieu":"CESSON SEVIGNE","departement":"35","divers":"OCC NATATION TRIATHLON triathlon@occnatation.fr http://occnatation.fr/","email":"triathlon@occnatation.fr"},{"event":"CHAMPIONNAT D'ILLE ET VLAINE","organisateur":null,"lieu":"FEINS","departement":"35","divers":"RENNES TRIATHLON 0223225485 - contact@feins-triathlon.com www.feins-triathlon.com","email":"contact@feins-triathlon.com"},{"event":"EMERAUDE EVENTS","organisateur":null,"lieu":"ST LUNAIRE/ST BRIAC/LANCIEUX","departement":"35","divers":"EMERAUDE EVENTS contact@emeraude-events.com www.emeraude-events.com","email":"contact@emeraude-events.com"},{"event":"EMERAUDE EVENTS","organisateur":null,"lieu":"ST LUNAIRE/ST BRIAC/LANCIEUX","departement":"35","divers":"EMERAUDE EVENTS contact@emeraude-events.com www.emeraude-events.com","email":"contact@emeraude-events.com"},{"event":"EMERAUDE EVENTS","organisateur":null,"lieu":"ST LUNAIRE/ST BRIAC/LANCIEUX","departement":"35","divers":"EMERAUDE EVENTS contact@emeraude-events.com www.emeraude-events.com","email":"contact@emeraude-events.com"},{"event":"DUATHLON SAINT SULPICE LA FORET 2018","organisateur":null,"lieu":"SAINT SULPICE LA FORET","departement":"35","divers":"ASC ST SULPICE LA FORET inscription.sslf.duathlon@gmail.com klikego","email":"inscription.sslf.duathlon@gmail.com"},{"event":"RUN AND BIKE","organisateur":null,"lieu":"PLOUAY","departement":"56","divers":"ECUREUILS DE PLOUAY TRIATHLON 0645283315 - ecureuilsdeplouaytriathlon@outlook.fr https://www.klikego.com","email":"ecureuilsdeplouaytriathlon@outlook.fr"},{"event":"ANIMATION RUN AND BIKE","organisateur":null,"lieu":"PLOERMEL","departement":"56","divers":"LYCéE LA TOUCHE 0616125036 - runandbike.latouche@gmail.com","email":"runandbike.latouche@gmail.com"},{"event":"RUN AND BIKE","organisateur":null,"lieu":"GOURIN","departement":"56","divers":"GOURIN TRIATHON gtdtriathlon@yahoo.fr KLIKEGO","email":"gtdtriathlon@yahoo.fr"},{"event":"RUN AND BIKE","organisateur":null,"lieu":"GRAND-CHAMP","departement":"56","divers":"LOCH NATURE 06-52-19-69-12 - conatct@loch-nature.fr loch-nature.fr","email":"conatct@loch-nature.fr"},{"event":"TRIATHLONS DE COETQUIDAN","organisateur":null,"lieu":"GUER","departement":"56","divers":"ASAEC COETQUIDAN TRIATHLON 06 22 61 90 89 - ast.coetquidan@gmail.com https://sites.google.com/view/asaeccoetquidantriathlon/accueil","email":"ast.coetquidan@gmail.com"},{"event":"TRIATHLONS DE COETQUIDAN","organisateur":null,"lieu":"GUER","departement":"56","divers":"ASAEC COETQUIDAN TRIATHLON 06 22 61 90 89 - ast.coetquidan@gmail.com https://sites.google.com/view/asaeccoetquidantriathlon/accueil","email":"ast.coetquidan@gmail.com"},{"event":"9èME TRIATHLON DAMGAN","organisateur":null,"lieu":"DAMGAN","departement":"56","divers":"OFFICE MUNICIPAL DES SPORTS MUZILLAC BILLIERS 06 66 79 98 69 - haudry.frederic@orange.fr www.muzillactriathlon.fr","email":"haudry.frederic@orange.fr"},{"event":"ANIMATHLON DES COLLèGES","organisateur":null,"lieu":"PLOUAY","departement":"56","divers":"ECUREUILS DE PLOUAY TRIATHLON 0645283315 - ecureuilsdeplouaytriathlon@outlook.fr","email":"ecureuilsdeplouaytriathlon@outlook.fr"},{"event":"TRI ET DU DES ECUREUILS DE PLOUAY","organisateur":null,"lieu":"PLOUAY","departement":"56","divers":"ECUREUILS DE PLOUAY TRIATHLON 0645283315 - ecureuilsdeplouaytriathlon@outlook.fr https://ecureuilsdeplouayt.wixsite.com/ecureuilstriathlon","email":"ecureuilsdeplouaytriathlon@outlook.fr"},{"event":"TRI ET DU DES ECUREUILS DE PLOUAY","organisateur":null,"lieu":"PLOUAY","departement":"56","divers":"ECUREUILS DE PLOUAY TRIATHLON 0645283315 - ecureuilsdeplouaytriathlon@outlook.fr https://ecureuilsdeplouayt.wixsite.com/ecureuilstriathlon","email":"ecureuilsdeplouaytriathlon@outlook.fr"},{"event":"AQUATHLON","organisateur":null,"lieu":"PONTIVY","departement":"56","divers":"PONTIVY TRIATHLON yann.lebrestec@orange.fr","email":"yann.lebrestec@orange.fr"},{"event":"AQUATHLON DES VéNèTES","organisateur":null,"lieu":"VANNES","departement":"56","divers":"VéNèTES TRIATHLON 0683221226 - venetestri-jclenne@laposte.net http://venetes-triathlon.super-h.fr","email":"venetestri-jclenne@laposte.net"},{"event":"2éME AQUATHLON DU TRIATHLON CLUB DE LOCMINE","organisateur":null,"lieu":"LOCMINE","departement":"56","divers":"TRIATHLON-CLUB-LOCMINE 02-97-41-20-88 - masseve0573@orange.fr","email":"masseve0573@orange.fr"},{"event":"2éME AQUATHLON DU TRIATHLON CLUB DE LOCMINE","organisateur":null,"lieu":"LOCMINE","departement":"56","divers":"TRIATHLON-CLUB-LOCMINE 02-97-41-20-88 - masseve0573@orange.fr","email":"masseve0573@orange.fr"},{"event":"TRIATBREIZH","organisateur":null,"lieu":"INZINZAC LOCHRIST","departement":"56","divers":"TRIATBREIZH infos@triatbreizh.com www.triatbreizh.com","email":"infos@triatbreizh.com"},{"event":"TRIATBREIZH","organisateur":null,"lieu":"INZINZAC LOCHRIST","departement":"56","divers":"TRIATBREIZH infos@triatbreizh.com www.triatbreizh.com","email":"infos@triatbreizh.com"},{"event":"TRI ALRé RACE","organisateur":null,"lieu":"AURAY","departement":"56","divers":"LE PAYS D'AURAY TRIATHLON  0689654896 - yhervio@yahoo.fr Klikego","email":"yhervio@yahoo.fr"},{"event":"TRIATHLONS DE L'éTANG DU TER","organisateur":null,"lieu":"LORIENT","departement":"56","divers":"LORIENT TRIATHLON FLK 0611642191 - denis@bretagnesud.net Klikego","email":"denis@bretagnesud.net"},{"event":"TRIATHLONS DE L'éTANG DU TER","organisateur":null,"lieu":"LORIENT","departement":"56","divers":"LORIENT TRIATHLON FLK 0611642191 - denis@bretagnesud.net Klikego","email":"denis@bretagnesud.net"},{"event":"TRISKEL RACE","organisateur":null,"lieu":"GUIDEL","departement":"56","divers":"GUIDEL TRIATHLON 0683015253 - laura.phelippe@gmail.com www.klikego.com","email":"laura.phelippe@gmail.com"},{"event":"TRISKEL RACE","organisateur":null,"lieu":"GUIDEL","departement":"56","divers":"GUIDEL TRIATHLON 0683015253 - laura.phelippe@gmail.com www.klikego.com","email":"laura.phelippe@gmail.com"},{"event":"TRIATHLON DE CARNAC","organisateur":null,"lieu":"CARNAC","departement":"56","divers":"TRIATHLé VANNES tricarnac-inscription@orange.fr www.triathlevannes.com","email":"tricarnac-inscription@orange.fr"},{"event":"TRIATHLON DE CARNAC","organisateur":null,"lieu":"CARNAC","departement":"56","divers":"TRIATHLé VANNES tricarnac-inscription@orange.fr www.triathlevannes.com","email":"tricarnac-inscription@orange.fr"},{"event":"TRI RELAIS 2018","organisateur":null,"lieu":"INZINZAC LOCHRIST","departement":"56","divers":"HENNEBONTTRIATHLON hennebonttriathlon@gmail.com trirelaisdublavet@gmail.com","email":"hennebonttriathlon@gmail.com"},{"event":"TRI RELAIS 2018","organisateur":null,"lieu":"INZINZAC LOCHRIST","departement":"56","divers":"HENNEBONTTRIATHLON hennebonttriathlon@gmail.com trirelaisdublavet@gmail.com","email":"trirelaisdublavet@gmail.com"},{"event":"TRIATHLON DE LA ROCHE BERNARD","organisateur":null,"lieu":"LA ROCHE BERNARD","departement":"56","divers":"TCPMUZILLAC 0666799869 - haudry.frederic@orange.fr","email":"haudry.frederic@orange.fr"},{"event":"RUN & BIKE","organisateur":null,"lieu":"QUEVEN","departement":"56","divers":"CLUB CYCLOTOURISTE QUéVENOIS 0660690076 - patrick.langlet6@wanadoo.fr http://www.ccquevenois.fr/","email":"patrick.langlet6@wanadoo.fr"}]